MANIFEST.in
README.md
setup.cfg
setup.py
py_instrumenting_zipkin.egg-info/PKG-INFO
py_instrumenting_zipkin.egg-info/SOURCES.txt
py_instrumenting_zipkin.egg-info/dependency_links.txt
py_instrumenting_zipkin.egg-info/requires.txt
py_instrumenting_zipkin.egg-info/top_level.txt
pytracing/__init__.py
pytracing/admin.py
pytracing/apitracer.py
pytracing/constants.py
pytracing/middleware.py
pytracing/models.py
pytracing/tests.py
pytracing/trace.py
pytracing/transporter.py
pytracing/views.py