Metadata-Version: 1.0
Name: py-instrumenting-zipkin
Version: 1.0.0
Summary: Zipkin based python instrumenting library to sends data using sync/async trasnporters.
Home-page: https://github.com/harkishan81001/py-instrumenting
Author: Hari Kishan
Author-email: hari.kishan81001@gmail.com
License: Apache License 2.0
Keywords: Django Zipkin Instrumentation
Platform: UNKNOWN
